AShelve/__init__.py
AShelve/main.py
ashelve-1.0.0.dist-info/METADATA
ashelve-1.0.0.dist-info/WHEEL
ashelve-1.0.0.dist-info/top_level.txt
ashelve-1.0.0.dist-info/RECORD
